aishield/__init__.py
aishield/aishield_api.py
aishield/configs.py
aishield/connection.py
aishield/constants.py
aishield/all_task/__init__.py
aishield/all_task/base.py
aishield/all_task/supply_chain.py
aishield/image_classification/__init__.py
aishield/image_classification/base_ic.py
aishield/image_classification/evasion.py
aishield/image_classification/extraction.py
aishield/image_classification/poision.py
aishield/image_segmentation/__init__.py
aishield/image_segmentation/base_is.py
aishield/image_segmentation/extraction.py
aishield/natural_language_processing/__init__.py
aishield/natural_language_processing/base_nlp.py
aishield/natural_language_processing/extraction.py
aishield/object_detection/__init__.py
aishield/object_detection/base_od.py
aishield/object_detection/evasion.py
aishield/object_detection/extraction.py
aishield/tabular_classification/__init__.py
aishield/tabular_classification/base_tc.py
aishield/tabular_classification/evasion.py
aishield/tabular_classification/extraction.py
aishield/text_recommendation/__init__.py
aishield/text_recommendation/base_tr.py
aishield/text_recommendation/extraction.py
aishield/timeseries_forecasting/__init__.py
aishield/timeseries_forecasting/base_tsf.py
aishield/timeseries_forecasting/extraction.py
aishield/utils/__init__.py
aishield/utils/exceptions.py
aishield/utils/logger.py
aishield/utils/util.py
tests/__init__.py
tests/test_aishield_api.py
aishield-0.1.7.dist-info/METADATA
aishield-0.1.7.dist-info/WHEEL
aishield-0.1.7.dist-info/top_level.txt
aishield-0.1.7.dist-info/RECORD
