Metadata-Version: 2.1
Name: aishield
Version: 0.1.7
Summary: AIShield provides the Python convenience package to allow users to seamlessly integrate AIShield Vulnerability Assessment and Defense capabilities into their AI development workflows.
Home-page: https://www.boschaishield.com/
Author: Contact AIShield
Author-email: aishield.contact@bosch.com
License: Apache License
Platform: UNKNOWN
Classifier: Programming Language :: Python :: 3
Classifier: License :: OSI Approved :: Apache Software License
Classifier: Operating System :: OS Independent
Requires-Dist: requests
